ezcrypt
