Metadata-Version: 1.1
Name: ezcrypt
Version: 1.0.0
Summary: A helper for encrypting bytes
Home-page: https://github.com/Zaeb0s/ez-crypt
Author: Christoffer Zakrisson
Author-email: christoffer_zakrisson@hotmail.com
License: MIT
Keywords: crypt,encrypt,decrypt,key,iv,easy
Platform: UNKNOWN
Classifier: Development Status :: 4 - Beta
Classifier: Programming Language :: Python :: 3.5
Classifier: Operating System :: POSIX :: Linux
Classifier: License :: OSI Approved :: MIT License
